Metadata-Version: 2.1
Name: ritprofile
Version: 0.0.2
Summary: ritprofile by Rit Engineer
Home-page: https://github.com/RitEngineer/RitProfile
Author: Rit Engineer
Author-email: kittikul_m@yahoo.com
License: MIT
Download-URL: https://github.com/RitEngineer/RitProfile/archive/v0.0.1.zip
Keywords: Profile,Rit,Rit Engineer
Platform: UNKNOWN
Classifier: Development Status :: 3 - Alpha
Classifier: Intended Audience :: Education
Classifier: Topic :: Utilities
Classifier: License :: OSI Approved :: MIT License
Classifier: Programming Language :: Python :: 3
Classifier: Programming Language :: Python :: 3.4
Classifier: Programming Language :: Python :: 3.5
Classifier: Programming Language :: Python :: 3.6
Classifier: Programming Language :: Python :: 3.7
Classifier: Programming Language :: Python :: 3.8
Classifier: Programming Language :: Python :: 3.9
License-File: LICENSE.txt
